[
    {
        "image": "/images/beyond-the-black-rainbow/TWELVETEN_6-26-1.jpg",
        "author": null,
        "title": "Beyond the Black Rainbow",
        "date": null,
        "dimensions": "Installation view",
        "media": null,
        "credit": "Photo: Mikey Mosher",
        "hidden": false,
        "available": false
    },
    {
        "image": "/images/beyond-the-black-rainbow/TWELVETEN_6-26-6.jpg",
        "author": null,
        "title": "Beyond the Black Rainbow",
        "date": null,
        "dimensions": "Installation view",
        "media": "From top left to bottom right: Tristan Higginbotham, 'Long Gravid', Justin Beachler, 'Power Talisman/Pop Apotheosis', Nico Ramirez Rosas, 'immaterial girl', Justin Beachler, 'Five grams alone in the darkness', Laveen Gammie, 'Untitled (boudoir floor)'",
        "credit": "Photo: Mikey Mosher",
        "hidden": false,
        "available": false
    },
    {
        "image": "/images/beyond-the-black-rainbow/TWELVETEN_6-26-72.jpg",
        "author": "Tristan Higginbotham",
        "title": "Long Gravid",
        "date": "2025",
        "dimensions": "9.5 x 4 x 2 in. (24.13 x 10.16 x 5.08  cm)",
        "media": "Found wood, debris, wire, acrylic, graphite",
        "credit": "Photo: Mikey Mosher",
        "hidden": false,
        "available": false
    },
    {
        "image": "/images/beyond-the-black-rainbow/TWELVETEN_6-26-71.jpg",
        "author": "Tristan Higginbotham",
        "title": "Long Gravid",
        "date": "2025",
        "dimensions": "9.5 x 4 x 2 in. (24.13 x 10.16 x 5.08  cm)",
        "media": "Found wood, debris, wire, acrylic, graphite",
        "credit": "Photo: Mikey Mosher",
        "hidden": false,
        "available": true
    },
    {
        "image": "/images/beyond-the-black-rainbow/TWELVETEN_6-26-76.jpg",
        "author": "Tristan Higginbotham",
        "title": "Long Gravid",
        "date": "2025",
        "dimensions": "detail",
        "media": "Found wood, debris, wire, acrylic, graphite",
        "credit": "Photo: Mikey Mosher",
        "hidden": false,
        "available": false
    },
    {
        "image": "/images/beyond-the-black-rainbow/TWELVETEN_6-26-59.jpg",
        "author": "Justin Beachler",
        "title": "Power Talisman / Pop Apotheosis",
        "date": "2025",
        "dimensions": "17 x 6 x 1 in. (43.18 x 15.24 x 2.54 cm)",
        "media": "1974 hardback copy of Carlos Casteneda Tales of Power, stone beaded necklaces, amethyst, magnet",
        "credit": "Photo: Mikey Mosher",
        "hidden": false,
        "available": true
    },
    {
        "image": "/images/beyond-the-black-rainbow/TWELVETEN_6-26-61.jpg",
        "author": "Justin Beachler",
        "title": "Power Talisman / Pop Apotheosis",
        "date": "2025",
        "dimensions": "detail",
        "media": "1974 hardback copy of Carlos Casteneda Tales of Power, stone beaded necklaces, amethyst, magnet",
        "credit": "Photo: Mikey Mosher",
        "hidden": false,
        "available": false
    },
    {
        "image": "/images/beyond-the-black-rainbow/TWELVETEN_6-26-22.jpg",
        "author": "Nico Ramirez Rosas",
        "title": "immaterial girl",
        "date": "2026",
        "dimensions": "12 x  60 in. (30.48 x 152.4 cm), 12 x  72 in. (30.48 x 182.88 cm), 12 x  60 in. (30.48 x 152.4 cm)",
        "media": "Oil, acrylic, tape, inkjet print on bedsheet",
        "credit": "Photo: Mikey Mosher",
        "hidden": false,
        "available": true
    },
    {
        "image": "/images/beyond-the-black-rainbow/TWELVETEN_6-26-24.jpg",
        "author": "Nico Ramirez Rosas",
        "title": "immaterial girl",
        "date": "2026",
        "dimensions": "detail",
        "media": "Oil, acrylic, tape, inkjet print on bedsheet",
        "credit": "Photo: Mikey Mosher",
        "hidden": false,
        "available": false
    },
    {
        "image": "/images/beyond-the-black-rainbow/TWELVETEN_6-26-26.jpg",
        "author": "Nico Ramirez Rosas",
        "title": "immaterial girl",
        "date": "2026",
        "dimensions": "detail",
        "media": "Oil, acrylic, tape, inkjet print on bedsheet",
        "credit": "Photo: Mikey Mosher",
        "hidden": false,
        "available": false
    },
    {
        "image": "/images/beyond-the-black-rainbow/TWELVETEN_6-26-2.jpg",
        "author": null,
        "title": "Beyond the Black Rainbow",
        "date": null,
        "dimensions": "Installation view",
        "media": "From top left to bottom right:  Nico Ramirez Rosas, 'immaterial girl', Justin Beachler, 'Power Talisman/Pop Apotheosis', Tristan Higginbotham, 'Winding my spring', Justin Beachler, 'Goddess Submission / Sex Magick Manifestation ritual', Laveen Gammie, 'Untitled (boudoir floor)'",
        "credit": "Photo: Mikey Mosher",
        "hidden": false,
        "available": false
    },
    {
        "image": "/images/beyond-the-black-rainbow/TWELVETEN_6-26-27.jpg",
        "author": "Justin Beachler",
        "title": "Five grams alone in the darkness",
        "date": "2025",
        "dimensions": "24 x 2 x 2  in. (60.96 x 5.08 x 5.08 cm)",
        "media": "Tropical sunset poster, sterling silver mushroom bracelet, wood",
        "credit": "Photo: Mikey Mosher",
        "hidden": false,
        "available": true
    },
    {
        "image": "/images/beyond-the-black-rainbow/TWELVETEN_6-26-28.jpg",
        "author": "Justin Beachler",
        "title": "Five grams alone in the darkness",
        "date": "2025",
        "dimensions": "detail",
        "media": "Tropical sunset poster, sterling silver mushroom bracelet, wood",
        "credit": "Photo: Mikey Mosher",
        "hidden": false,
        "available": false
    },
    {
        "image": "/images/beyond-the-black-rainbow/TWELVETEN_6-26-55.jpg",
        "author": "Tristan Higginbotham",
        "title": "Winding my spring",
        "date": "2025",
        "dimensions": "11 x 7.5 x 4.5  in. (27.94 x 19.05 x  11.43 cm)",
        "media": "Clam shells, string, resin clay, seed pods, acrylic, graphite",
        "credit": "Photo: Mikey Mosher",
        "hidden": false,
        "available": false
    },
    {
        "image": "/images/beyond-the-black-rainbow/TWELVETEN_6-26-54.jpg",
        "author": "Tristan Higginbotham",
        "title": "Winding my spring",
        "date": "2025",
        "dimensions": "11 x 7.5 x 4.5  in. (27.94 x 19.05 x  11.43 cm)",
        "media": "Clam shells, string, resin clay, seed pods, acrylic, graphite",
        "credit": "Photo: Mikey Mosher",
        "hidden": false,
        "available": true
    },
    {
        "image": "/images/beyond-the-black-rainbow/TWELVETEN_6-26-48.jpg",
        "author": "Justin Beachler",
        "title": "Goddess Submission / Sex Magick Manifestation ritual",
        "date": "2025",
        "dimensions": "3.5 x 10 x 8  in. (8.89 x 25.4  x 20.32  cm)",
        "media": "Framed Caryatid picture, Acrylic picture frame, 1961 Playboy clipping, manifestation pyramid, amethyst phallus",
        "credit": "Photo: Mikey Mosher",
        "hidden": false,
        "available": false
    },
    {
        "image": "/images/beyond-the-black-rainbow/TWELVETEN_6-26-50.jpg",
        "author": "Justin Beachler",
        "title": "Goddess Submission / Sex Magick Manifestation ritual",
        "date": "2025",
        "dimensions": "3.5 x 10 x 8  in. (8.89 x 25.4  x 20.32  cm)",
        "media": "Framed Caryatid picture, Acrylic picture frame, 1961 Playboy clipping, manifestation pyramid, amethyst phallus",
        "credit": "Photo: Mikey Mosher",
        "hidden": false,
        "available": true
    },
    {
        "image": "/images/beyond-the-black-rainbow/TWELVETEN_6-26-53.jpg",
        "author": "Justin Beachler",
        "title": "Goddess Submission / Sex Magick Manifestation ritual",
        "date": "2025",
        "dimensions": "detail",
        "media": "Framed Caryatid picture, Acrylic picture frame, 1961 Playboy clipping, manifestation pyramid, amethyst phallus",
        "credit": "Photo: Mikey Mosher",
        "hidden": false,
        "available": false
    },
    {
        "image": "/images/beyond-the-black-rainbow/TWELVETEN_6-26-4.jpg",
        "author": null,
        "title": "Beyond the Black Rainbow",
        "date": null,
        "dimensions": "Installation view",
        "media": null,
        "credit": "Photo: Mikey Mosher",
        "hidden": false,
        "available": false
    },
    {
        "image": "/images/beyond-the-black-rainbow/TWELVETEN_6-26-41.jpg",
        "author": "Nico Ramirez Rosas",
        "title": "Carolyn chronic",
        "date": "2026",
        "dimensions": "3 x 4.25 x 3.25 in (7.62 x 10.795 x 7.62 cm)",
        "media": "Ceramic pipe, found objects, inkjet print, polly plastics on a fake ID",
        "credit": "Photo: Mikey Mosher",
        "hidden": false,
        "available": false
    },
    {
        "image": "/images/beyond-the-black-rainbow/TWELVETEN_6-26-42.jpg",
        "author": "Nico Ramirez Rosas",
        "title": "Carolyn chronic",
        "date": "2026",
        "dimensions": "3 x 4.25 x 3.25 in (7.62 x 10.795 x 7.62 cm)",
        "media": "Ceramic pipe, found objects, inkjet print, polly plastics on a fake ID",
        "credit": "Photo: Mikey Mosher",
        "hidden": false,
        "available": true
    },
    {
        "image": "/images/beyond-the-black-rainbow/TWELVETEN_6-26-3.jpg",
        "author": null,
        "title": "Beyond the Black Rainbow",
        "date": null,
        "dimensions": "Installation view",
        "media": "From left to right: Laveen Gammie, 'Decoy (Calling out of context)', Tristan Higginbotham, 'INKlings', Laveen Gammie, '(but , another thought) &amp;…', Nico Ramirez Rosas, 'Carolyn chronic', Laveen Gammie, 'Untitled (boudoir floor)'",
        "credit": "Photo: Mikey Mosher",
        "hidden": false,
        "available": false
    },
    {
        "image": "/images/beyond-the-black-rainbow/TWELVETEN_6-26-64.jpg",
        "author": "Laveen Gammie",
        "title": "(but , another thought) &amp;…",
        "date": "2026",
        "dimensions": "10 x 9 x 0.5 in. (25.4 x 22.86 x 1.27 cm)",
        "media": "Gypsum cast, spackle, paint",
        "credit": "Photo: Mikey Mosher",
        "hidden": false,
        "available": false
    },
    {
        "image": "/images/beyond-the-black-rainbow/TWELVETEN_6-26-65.jpg",
        "author": "Laveen Gammie",
        "title": "(but , another thought) &amp;…",
        "date": "2026",
        "dimensions": "10 x 9 x 0.5 in. (25.4 x 22.86 x 1.27 cm)",
        "media": "Gypsum cast, spackle, paint",
        "credit": "Photo: Mikey Mosher",
        "hidden": false,
        "available": true
    },
    {
        "image": "/images/beyond-the-black-rainbow/TWELVETEN_6-26-67.jpg",
        "author": "Tristan Higginbotham",
        "title": "INKlings",
        "date": "2025",
        "dimensions": "5 x 6.5 x 2 in. (12.7 x 16.51 x 5.08 cm)",
        "media": "Found mirror, spoon, suction cups, petrified frog, acrylic, resin, clay",
        "credit": "Photo: Mikey Mosher",
        "hidden": false,
        "available": true
    },
    {
        "image": "/images/beyond-the-black-rainbow/TWELVETEN_6-26-68.jpg",
        "author": "Tristan Higginbotham",
        "title": "INKlings",
        "date": "2025",
        "dimensions": "detail",
        "media": "Found mirror, spoon, suction cups, petrified frog, acrylic, resin, clay",
        "credit": "Photo: Mikey Mosher",
        "hidden": false,
        "available": false
    },
    {
        "image": "/images/beyond-the-black-rainbow/TWELVETEN_6-26-65.jpg",
        "author": "Laveen Gammie",
        "title": "(but , another thought) &amp;…",
        "date": "2026",
        "dimensions": "10 x 9 x 0.5 in. (25.4 x 22.86 x 1.27 cm)",
        "media": "Gypsum cast, spackle, paint",
        "credit": "Photo: Mikey Mosher",
        "hidden": false,
        "available": true
    }
]
